{"name":"phoneformat.js","assets":[{"files":["phone-format-amd.min.js","phone-format-amd.min.js.map","phone-format-exports.min.js","phone-format-exports.min.js.map","phone-format-global.min.js","phone-format-global.min.js.map","phone-format.min.js","phone-format.min.js.map"],"version":"1.0.1","mainfile":"phone-format.min.js"},{"files":["phone-format-amd.min.js","phone-format-amd.min.js.map","phone-format-exports.min.js","phone-format-exports.min.js.map","phone-format-global.min.js","phone-format-global.min.js.map","phone-format.min.js","phone-format.min.js.map"],"version":"1.0.2","mainfile":"phone-format.min.js"},{"files":["phone-format-amd.min.js","phone-format-amd.min.js.map","phone-format-exports.min.js","phone-format-exports.min.js.map","phone-format-global.min.js","phone-format-global.min.js.map","phone-format.min.js","phone-format.min.js.map"],"version":"1.0.3","mainfile":"phone-format.min.js"},{"files":["phone-format-amd.min.js","phone-format-amd.min.js.map","phone-format-exports.min.js","phone-format-exports.min.js.map","phone-format-global.min.js","phone-format-global.min.js.map","phone-format.min.js","phone-format.min.js.map"],"version":"1.0.4","mainfile":"phone-format.min.js"},{"files":["phone-format-amd.min.js","phone-format-amd.min.js.map","phone-format-exports.min.js","phone-format-exports.min.js.map","phone-format-global.min.js","phone-format-global.min.js.map","phone-format.min.js","phone-format.min.js.map"],"version":"1.0.5","mainfile":"phone-format.min.js"}],"versions":["1.0.5","1.0.4","1.0.3","1.0.2","1.0.1"],"zip":"phoneformat.js.zip","author":"Al Beebe","github":"https://github.com/albeebe/phoneformat.js","homepage":"http://www.phoneformat.com/","description":"A javascript phone formatter","mainfile":"phone-format.min.js","lastversion":"1.0.5"}