{"name":"wysihtml5","assets":[{"files":["wysihtml5-0.3.0.js","wysihtml5-0.3.0.min.js"],"version":"0.3.0","mainfile":"wysihtml5-0.3.0.min.js"}],"versions":["0.3.0"],"zip":"wysihtml5.zip","author":"XING Developers","github":"https://github.com/xing/wysihtml5","homepage":"http://xing.github.com/wysihtml5/","description":"Open source rich text editor based on HTML5 and the progressive-enhancement approach. Uses a sophisticated security concept and aims to generate fully valid HTML5 markup by preventing unmaintainable tag soups and inline styles. ","mainfile":"wysihtml5-0.3.0.min.js","lastversion":"0.3.0"}