{"name":"ng-pdfviewer","assets":[{"files":["ng-pdfviewer.min.js","ng-pdfviewer.min.map"],"version":"0.2.0","mainfile":"ng-pdfviewer.min.js"},{"files":["ng-pdfviewer.min.js"],"version":"0.1.0","mainfile":"ng-pdfviewer.min.js"},{"files":["ng-pdfviewer.min.js","ng-pdfviewer.min.map"],"version":"0.2.1","mainfile":"ng-pdfviewer.min.js"}],"versions":["0.2.1","0.2.0","0.1.0"],"zip":"ng-pdfviewer.zip","mainfile":"ng-pdfviewer.min.js","author":"Andreas Krennmair <ak@synflood.at>","lastversion":"0.2.1","homepage":null,"description":"AngularJS PDF viewer directive using pdf.js.","github":"https://github.com/akrennmair/ng-pdfviewer.git"}