{"name":"libil","assets":[{"files":["libil.js","libil.min.js"],"version":"0.1.1","mainfile":"libil.min.js"},{"files":["libil.js","libil.min.js"],"version":"0.1.2","mainfile":"libil.min.js"}],"versions":["0.1.2","0.1.1"],"zip":"libil.zip","mainfile":"libil.min.js","author":null,"lastversion":"0.1.2","homepage":"https://github.com/lynxluna/libil.js","description":"Libil is a JavaScript library to process string for Bahasa Walikan. It supports Yogyakarta and Malang Style","github":"https://github.com/lynxluna/libil.git"}