{"name":"js-xlsx","assets":[{"files":["cpexcel.js","jszip.js","ods.js","xlsx.core.min.js","xlsx.core.min.map","xlsx.full.min.js","xlsx.full.min.map","xlsx.js","xlsx.min.js","xlsx.min.map"],"version":"0.7.11","mainfile":"xlsx.min.js"},{"files":["cpexcel.js","jszip.js","ods.js","xlsx.core.min.js","xlsx.core.min.map","xlsx.full.min.js","xlsx.full.min.map","xlsx.js","xlsx.min.js","xlsx.min.map"],"version":"0.8.0","mainfile":"xlsx.min.js"},{"files":["cpexcel.js","jszip.js","ods.js","xlsx.core.min.js","xlsx.core.min.map","xlsx.full.min.js","xlsx.full.min.map","xlsx.js","xlsx.min.js","xlsx.min.map"],"version":"0.8.1","mainfile":"xlsx.min.js"},{"files":["cpexcel.js","jszip.js","ods.js","ods.min.js","ods.min.map","xlsx.core.min.js","xlsx.core.min.map","xlsx.full.min.js","xlsx.full.min.map","xlsx.js","xlsx.min.js","xlsx.min.map"],"version":"0.8.3","mainfile":"xlsx.min.js"},{"files":["cpexcel.js","jszip.js","ods.js","ods.min.js","ods.min.map","xlsx.core.min.js","xlsx.core.min.map","xlsx.full.min.js","xlsx.full.min.map","xlsx.js","xlsx.min.js","xlsx.min.map"],"version":"0.8.2","mainfile":"xlsx.min.js"},{"files":["cpexcel.js","jszip.js","ods.js","ods.min.js","ods.min.map","xlsx.core.min.js","xlsx.core.min.map","xlsx.full.min.js","xlsx.full.min.map","xlsx.js","xlsx.min.js","xlsx.min.map"],"version":"0.8.4","mainfile":"xlsx.min.js"},{"files":["cpexcel.js","jszip.js","ods.js","ods.min.js","ods.min.map","xlsx.core.min.js","xlsx.core.min.map","xlsx.full.min.js","xlsx.full.min.map","xlsx.js","xlsx.min.js","xlsx.min.map"],"version":"0.8.5","mainfile":"xlsx.min.js"},{"files":["cpexcel.js","jszip.js","ods.js","ods.min.js","ods.min.map","xlsx.core.min.js","xlsx.core.min.map","xlsx.full.min.js","xlsx.full.min.map","xlsx.js","xlsx.min.js","xlsx.min.map"],"version":"0.8.7","mainfile":"xlsx.min.js"},{"files":["cpexcel.js","jszip.js","ods.js","ods.min.js","ods.min.map","xlsx.core.min.js","xlsx.core.min.map","xlsx.full.min.js","xlsx.full.min.map","xlsx.js","xlsx.min.js","xlsx.min.map"],"version":"0.8.8","mainfile":"xlsx.min.js"},{"files":["cpexcel.js","jszip.js","xlsx.core.min.js","xlsx.core.min.map","xlsx.full.min.js","xlsx.full.min.map","xlsx.js","xlsx.min.js","xlsx.min.map"],"version":"0.9.0","mainfile":"xlsx.min.js"},{"files":["cpexcel.js","jszip.js","xlsx.core.min.js","xlsx.core.min.map","xlsx.full.min.js","xlsx.full.min.map","xlsx.js","xlsx.min.js","xlsx.min.map"],"version":"0.9.1","mainfile":"xlsx.min.js"},{"files":["cpexcel.js","jszip.js","xlsx.core.min.js","xlsx.core.min.map","xlsx.full.min.js","xlsx.full.min.map","xlsx.js","xlsx.min.js","xlsx.min.map"],"version":"0.9.10","mainfile":"xlsx.min.js"},{"files":["cpexcel.js","jszip.js","xlsx.core.min.js","xlsx.core.min.map","xlsx.full.min.js","xlsx.full.min.map","xlsx.js","xlsx.min.js","xlsx.min.map"],"version":"0.9.11","mainfile":"xlsx.min.js"},{"files":["cpexcel.js","jszip.js","xlsx.core.min.js","xlsx.core.min.map","xlsx.full.min.js","xlsx.full.min.map","xlsx.js","xlsx.min.js","xlsx.min.map"],"version":"0.9.12","mainfile":"xlsx.min.js"},{"files":["cpexcel.js","jszip.js","xlsx.core.min.js","xlsx.core.min.map","xlsx.full.min.js","xlsx.full.min.map","xlsx.js","xlsx.min.js","xlsx.min.map"],"version":"0.9.2","mainfile":"xlsx.min.js"},{"files":["cpexcel.js","jszip.js","xlsx.core.min.js","xlsx.core.min.map","xlsx.full.min.js","xlsx.full.min.map","xlsx.js","xlsx.min.js","xlsx.min.map"],"version":"0.9.3","mainfile":"xlsx.min.js"},{"files":["cpexcel.js","jszip.js","xlsx.core.min.js","xlsx.core.min.map","xlsx.full.min.js","xlsx.full.min.map","xlsx.js","xlsx.min.js","xlsx.min.map"],"version":"0.9.4","mainfile":"xlsx.min.js"},{"files":["cpexcel.js","jszip.js","xlsx.core.min.js","xlsx.core.min.map","xlsx.full.min.js","xlsx.full.min.map","xlsx.js","xlsx.min.js","xlsx.min.map"],"version":"0.9.5","mainfile":"xlsx.min.js"},{"files":["cpexcel.js","jszip.js","xlsx.core.min.js","xlsx.core.min.map","xlsx.full.min.js","xlsx.full.min.map","xlsx.js","xlsx.min.js","xlsx.min.map"],"version":"0.9.6","mainfile":"xlsx.min.js"},{"files":["cpexcel.js","jszip.js","xlsx.core.min.js","xlsx.core.min.map","xlsx.full.min.js","xlsx.full.min.map","xlsx.js","xlsx.min.js","xlsx.min.map"],"version":"0.9.7","mainfile":"xlsx.min.js"},{"files":["cpexcel.js","jszip.js","xlsx.core.min.js","xlsx.core.min.map","xlsx.full.min.js","xlsx.full.min.map","xlsx.js","xlsx.min.js","xlsx.min.map"],"version":"0.9.8","mainfile":"xlsx.min.js"},{"files":["cpexcel.js","jszip.js","xlsx.core.min.js","xlsx.core.min.map","xlsx.full.min.js","xlsx.full.min.map","xlsx.js","xlsx.min.js","xlsx.min.map"],"version":"0.9.9","mainfile":"xlsx.min.js"}],"versions":["0.9.12","0.9.11","0.9.10","0.9.9","0.9.8","0.9.7","0.9.6","0.9.5","0.9.4","0.9.3","0.9.2","0.9.1","0.9.0","0.8.8","0.8.7","0.8.5","0.8.4","0.8.3","0.8.2","0.8.1","0.8.0","0.7.11"],"zip":"js-xlsx.zip","author":"Anonymous","github":"https://github.com/SheetJS/js-xlsx","homepage":"http://sheetjs.com","description":"XLSX / XLSM / XLSB (Excel 2007+ Spreadsheet) / ODS parser and writer","mainfile":"xlsx.min.js","lastversion":"0.9.12"}