{"name":"glassbox","assets":[{"files":["glassbox/glassbox-min.js","glassbox/glassbox.js","glassbox/skins/blank.gif","glassbox/skins/exitButton.png","glassbox/skins/default/bottom.png","glassbox/skins/default/bottomleft.png","glassbox/skins/default/bottomright.png","glassbox/skins/default/left.png","glassbox/skins/default/right.png","glassbox/skins/default/top.png","glassbox/skins/default/topleft.png","glassbox/skins/default/topright.png","glassbox/skins/facebookstyle/bottom.png","glassbox/skins/facebookstyle/bottomleft.png","glassbox/skins/facebookstyle/bottomright.png","glassbox/skins/facebookstyle/left.png","glassbox/skins/facebookstyle/right.png","glassbox/skins/facebookstyle/top.png","glassbox/skins/facebookstyle/topleft.png","glassbox/skins/facebookstyle/topright.png","glassbox/skins/greyline/bottom.png","glassbox/skins/greyline/bottomleft.png","glassbox/skins/greyline/bottomright.png","glassbox/skins/greyline/center.png","glassbox/skins/greyline/left.png","glassbox/skins/greyline/right.png","glassbox/skins/greyline/top.png","glassbox/skins/greyline/topleft.png","glassbox/skins/greyline/topright.png","glassbox/skins/noline/bottom.png","glassbox/skins/noline/bottomleft.png","glassbox/skins/noline/bottomright.png","glassbox/skins/noline/left.png","glassbox/skins/noline/right.png","glassbox/skins/noline/top.png","glassbox/skins/noline/topleft.png","glassbox/skins/noline/topright.png","glassbox/skins/white/bottom.png","glassbox/skins/white/bottomleft.png","glassbox/skins/white/bottomright.png","glassbox/skins/white/left.png","glassbox/skins/white/right.png","glassbox/skins/white/top.png","glassbox/skins/white/topleft.png","glassbox/skins/white/topright.png"],"version":"2.0.0","mainfile":"glassbox/glassbox-min.js"}],"versions":["2.0.0"],"zip":"glassbox.zip","author":"Uli Preuss","github":"","homepage":"http://www.glassbox-js.com/","description":"GlassBox is a lightweight JavaScript User Interface (UI) library, which use Prototype and Script.aculo.us for some effects. GlassBox lets you easily build lucent borders, colorful layouts and Flash-like effects.","mainfile":"glassbox/glassbox-min.js","lastversion":"2.0.0"}