{"name":"jquery.lazyload","assets":[{"files":["jquery.lazyload.js","jquery.lazyload.min.js"],"version":"1.6.0","mainfile":"jquery.lazyload.min.js"},{"files":["jquery.lazyload.js","jquery.lazyload.min.js"],"version":"1.7.0","mainfile":"jquery.lazyload.min.js"},{"files":["jquery.lazyload.js","jquery.lazyload.min.js"],"version":"1.7.1","mainfile":"jquery.lazyload.min.js"},{"files":["jquery.lazyload.js","jquery.lazyload.min.js"],"version":"1.7.2","mainfile":"jquery.lazyload.min.js"},{"files":["jquery.lazyload.js","jquery.lazyload.min.js"],"version":"1.8.0","mainfile":"jquery.lazyload.min.js"},{"files":["jquery.lazyload.js","jquery.lazyload.min.js"],"version":"1.8.1","mainfile":"jquery.lazyload.min.js"},{"files":["jquery.lazyload.js","jquery.lazyload.min.js"],"version":"1.8.2","mainfile":"jquery.lazyload.min.js"},{"files":["jquery.lazyload.js","jquery.lazyload.min.js"],"version":"1.8.3","mainfile":"jquery.lazyload.min.js"},{"files":["jquery.lazyload.js","jquery.lazyload.min.js"],"version":"1.8.4","mainfile":"jquery.lazyload.min.js"},{"files":["jquery.lazyload.js","jquery.lazyload.min.js"],"version":"1.8.5","mainfile":"jquery.lazyload.min.js"},{"files":["jquery.lazyload.js","jquery.lazyload.min.js"],"version":"1.9.0","mainfile":"jquery.lazyload.min.js"},{"files":["jquery.lazyload.js","jquery.lazyload.min.js"],"version":"1.9.1","mainfile":"jquery.lazyload.min.js"},{"files":["jquery.lazyload.js","jquery.lazyload.min.js"],"version":"1.9.3","mainfile":"jquery.lazyload.min.js"}],"versions":["1.9.3","1.9.1","1.9.0","1.8.5","1.8.4","1.8.3","1.8.2","1.8.1","1.8.0","1.7.2","1.7.1","1.7.0","1.6.0"],"zip":"jquery.lazyload.zip","author":"Mika Tuupola","github":"https://github.com/tuupola/jquery_lazyload","homepage":"http://www.appelsiini.net/projects/lazyload","description":"Lazy Load is a jQuery plugin written in JavaScript. It delays loading of images in long web pages. Images outside of viewport (visible part of web page) wont be loaded before user scrolls to them.","mainfile":"jquery.lazyload.min.js","lastversion":"1.9.3"}