{"name":"lemonade","assets":[{"files":["lemonade.min.css"],"version":"2","mainfile":"lemonade.min.css"},{"files":["lemonade.css","lemonade.min.css"],"version":"1.1","mainfile":"lemonade.min.css"},{"files":["lemonade.css","lemonade.min.css"],"version":"2.1","mainfile":"lemonade.min.css"},{"files":["lemonade.css","lemonade.min.css"],"version":"2.1.0","mainfile":"lemonade.min.css"},{"files":["lemonade.css","lemonade.min.css"],"version":"2.5","mainfile":"lemonade.min.css"}],"versions":["2.5","2.1.0","2.1","2","1.1"],"zip":"lemonade.zip","mainfile":"lemonade.min.css","author":"Joe Richardson","lastversion":"2.5","homepage":"http://lemonade.im","description":"lemonade","github":"https://github.com/dope/lemonade"}