{"name":"fluxify","assets":[{"files":["fluxify.js","fluxify.min.js"],"version":"0.2.1","mainfile":"fluxify.min.js"},{"files":["fluxify.js","fluxify.min.js"],"version":"0.2.2","mainfile":"fluxify.min.js"},{"files":["fluxify.js","fluxify.min.js"],"version":"0.2.3","mainfile":"fluxify.min.js"}],"versions":["0.2.3","0.2.2","0.2.1"],"zip":"fluxify.zip","mainfile":"fluxify.min.js","author":{"name":"Javi Marquez","url":"http://arqex.com"},"lastversion":"0.2.3","homepage":null,"description":"The simplest flux implementation","github":"git+https://github.com/arqex/fluxify.git"}