{"name":"pubnub","assets":[{"files":["pubnub.min.js"],"version":"3.1.2","mainfile":"pubnub.min.js"},{"files":["pubnub-3.4.2.min.js","pubnub.min.js"],"version":"3.4.2","mainfile":"pubnub.min.js"},{"files":["pubnub.min.js"],"version":"3.4.5","mainfile":"pubnub.min.js"},{"files":["pubnub.js","pubnub.min.js"],"version":"3.4.6","mainfile":"pubnub.min.js"},{"files":["pubnub.min.js"],"version":"3.5.3","mainfile":"pubnub.min.js"},{"files":["pubnub.js","pubnub.min.js"],"version":"3.5.4","mainfile":"pubnub.min.js"},{"files":["pubnub.js","pubnub.min.js"],"version":"3.5.48","mainfile":"pubnub.min.js"},{"files":["pubnub.js","pubnub.min.js"],"version":"3.6.1","mainfile":"pubnub.min.js"},{"files":["pubnub.js","pubnub.min.js"],"version":"3.6.2","mainfile":"pubnub.min.js"},{"files":["pubnub.js","pubnub.min.js"],"version":"3.6.3","mainfile":"pubnub.min.js"},{"files":["pubnub.js","pubnub.min.js"],"version":"3.6.7","mainfile":"pubnub.min.js"},{"files":["pubnub.js","pubnub.min.js"],"version":"3.7.1","mainfile":"pubnub.min.js"},{"files":["pubnub.js","pubnub.min.js"],"version":"3.7.7","mainfile":"pubnub.min.js"}],"versions":["3.7.7","3.7.1","3.6.7","3.6.3","3.6.2","3.6.1","3.5.48","3.5.4","3.5.3","3.4.6","3.4.5","3.4.2","3.1.2"],"zip":"pubnub.zip","mainfile":"pubnub.min.js","author":null,"lastversion":"3.7.7","homepage":"http://www.pubnub.com/","description":"PubNub, a new kind of Cloud-Hosted Broadcasting Service for Mass Communication.","github":"https://github.com/pubnub/pubnub-api.git"}