{"name":"slimbox","assets":[{"files":["css/closelabel.gif","css/loading.gif","css/nextlabel.gif","css/prevlabel.gif","css/slimbox2-rtl.css","css/slimbox2.css","extra/android-market.js","extra/autoactivation.js","extra/fix-urls.js","extra/flickr.js","extra/picasaweb.js","js/slimbox2.js"],"version":"2.0.4","mainfile":"js/slimbox2.min.js"},{"files":["css/closelabel.gif","css/loading.gif","css/nextlabel.gif","css/prevlabel.gif","css/slimbox2-rtl.css","css/slimbox2.css","extra/autoactivation.js","extra/fix-urls.js","extra/flickr.js","extra/picasaweb.js","js/slimbox2.js","js/slimbox2.min.js"],"version":"2.0.5","mainfile":"js/slimbox2.min.js"}],"versions":["2.0.5","2.0.4"],"zip":"slimbox.zip","author":"Christophe Beyls","github":"","homepage":"http://www.digitalia.be/software/slimbox2","description":"Slimbox is a 4 KB visual clone of the popular Lightbox 2 script by Lokesh Dhakar, written using the jQuery javascript library (in version 2) or the MooTools javascript framework (in version 1). It was designed to be very small, efficient, standards-friendly, fully customizable, more convenient and 100% compatible with the original Lightbox 2.","mainfile":"js/slimbox2.min.js","lastversion":"2.0.5"}