{"name":"jquery.chained","assets":[{"files":["jquery.chained.js","jquery.chained.min.js","jquery.chained.remote.js","jquery.chained.remote.min.js"],"version":"0.9.4","mainfile":"jquery.chained.min.js"},{"files":["jquery.chained.js","jquery.chained.min.js","jquery.chained.remote.js","jquery.chained.remote.min.js"],"version":"0.9.8","mainfile":"jquery.chained.min.js"},{"files":["jquery.chained.js","jquery.chained.min.js","jquery.chained.remote.js","jquery.chained.remote.min.js"],"version":"0.9.9","mainfile":"jquery.chained.min.js"}],"versions":["0.9.9","0.9.8","0.9.4"],"zip":"jquery.chained.zip","author":"Mika Tuupola","github":"https://github.com/tuupola/jquery_chained","homepage":"http://www.appelsiini.net/projects/chained","description":"Chained is simple jQuery plugin for chained selects. You can choose from two different versions. Use jquery.chained.js if you do not want to make external queries for setting content of child selects. This version uses classnames of select options to decide content.","mainfile":"jquery.chained.min.js","lastversion":"0.9.9"}