{"name":"bluebird","assets":[{"files":["bluebird.js","bluebird.min.js","bluebird_debug.js","bluebird_debug.min.js","bluebird_sync.js","bluebird_sync.min.js"],"version":"0.7.10-1","mainfile":"bluebird.min.js"},{"files":["bluebird.js","bluebird.min.js"],"version":"1.0.0","mainfile":"bluebird.min.js"},{"files":["bluebird.js","bluebird.min.js"],"version":"1.2.1","mainfile":"bluebird.min.js"},{"files":["bluebird.js","bluebird.min.js"],"version":"1.2.2","mainfile":"bluebird.min.js"},{"files":["bluebird.js","bluebird.min.js"],"version":"2.10.0","mainfile":"bluebird.min.js"},{"files":["bluebird.js","bluebird.min.js"],"version":"2.10.1","mainfile":"bluebird.min.js"},{"files":["bluebird.js","bluebird.min.js"],"version":"2.10.2","mainfile":"bluebird.min.js"},{"files":["bluebird.js","bluebird.min.js"],"version":"2.11.0","mainfile":"bluebird.min.js"},{"files":["bluebird.js","bluebird.min.js"],"version":"2.3.10","mainfile":"bluebird.min.js"},{"files":["bluebird.js","bluebird.min.js"],"version":"2.3.11","mainfile":"bluebird.min.js"},{"files":["bluebird.js","bluebird.min.js"],"version":"2.3.6","mainfile":"bluebird.min.js"},{"files":["bluebird.js","bluebird.min.js"],"version":"2.3.9","mainfile":"bluebird.min.js"},{"files":["bluebird.js","bluebird.min.js"],"version":"2.4.0","mainfile":"bluebird.min.js"},{"files":["bluebird.js","bluebird.min.js"],"version":"2.4.1","mainfile":"bluebird.min.js"},{"files":["bluebird.js","bluebird.min.js"],"version":"2.4.2","mainfile":"bluebird.min.js"},{"files":["bluebird.js","bluebird.min.js"],"version":"2.4.3","mainfile":"bluebird.min.js"},{"files":["bluebird.js","bluebird.min.js"],"version":"2.5.0","mainfile":"bluebird.min.js"},{"files":["bluebird.js","bluebird.min.js"],"version":"2.5.1","mainfile":"bluebird.min.js"},{"files":["bluebird.js","bluebird.min.js"],"version":"2.5.2","mainfile":"bluebird.min.js"},{"files":["bluebird.js","bluebird.min.js"],"version":"2.5.3","mainfile":"bluebird.min.js"},{"files":["bluebird.js","bluebird.min.js"],"version":"2.6.0","mainfile":"bluebird.min.js"},{"files":["bluebird.js","bluebird.min.js"],"version":"2.6.1","mainfile":"bluebird.min.js"},{"files":["bluebird.js","bluebird.min.js"],"version":"2.6.2","mainfile":"bluebird.min.js"},{"files":["bluebird.js","bluebird.min.js"],"version":"2.6.3","mainfile":"bluebird.min.js"},{"files":["bluebird.js","bluebird.min.js"],"version":"2.6.4","mainfile":"bluebird.min.js"},{"files":["bluebird.js","bluebird.min.js"],"version":"2.7.0","mainfile":"bluebird.min.js"},{"files":["bluebird.js","bluebird.min.js"],"version":"2.7.1","mainfile":"bluebird.min.js"},{"files":["bluebird.js","bluebird.min.js"],"version":"2.8.0","mainfile":"bluebird.min.js"},{"files":["bluebird.js","bluebird.min.js"],"version":"2.8.1","mainfile":"bluebird.min.js"},{"files":["bluebird.js","bluebird.min.js"],"version":"2.8.2","mainfile":"bluebird.min.js"},{"files":["bluebird.js","bluebird.min.js"],"version":"2.9.0","mainfile":"bluebird.min.js"},{"files":["bluebird.js","bluebird.min.js"],"version":"2.9.1","mainfile":"bluebird.min.js"},{"files":["bluebird.js","bluebird.min.js"],"version":"2.9.10","mainfile":"bluebird.min.js"},{"files":["bluebird.js","bluebird.min.js"],"version":"2.9.11","mainfile":"bluebird.min.js"},{"files":["bluebird.js","bluebird.min.js"],"version":"2.9.12","mainfile":"bluebird.min.js"},{"files":["bluebird.js","bluebird.min.js"],"version":"2.9.13","mainfile":"bluebird.min.js"},{"files":["bluebird.js","bluebird.min.js"],"version":"2.9.14","mainfile":"bluebird.min.js"},{"files":["bluebird.js","bluebird.min.js"],"version":"2.9.15","mainfile":"bluebird.min.js"},{"files":["bluebird.js","bluebird.min.js"],"version":"2.9.16","mainfile":"bluebird.min.js"},{"files":["bluebird.core.js","bluebird.core.min.js","bluebird.js","bluebird.min.js"],"version":"3.4.7","mainfile":"bluebird.min.js"},{"files":["bluebird.core.js","bluebird.core.min.js","bluebird.js","bluebird.min.js"],"version":"3.4.6","mainfile":"bluebird.min.js"},{"files":["bluebird.core.js","bluebird.core.min.js","bluebird.js","bluebird.min.js"],"version":"3.4.5","mainfile":"bluebird.min.js"},{"files":["bluebird.core.js","bluebird.core.min.js","bluebird.js","bluebird.min.js"],"version":"3.4.4","mainfile":"bluebird.min.js"},{"files":["bluebird.core.js","bluebird.core.min.js","bluebird.js","bluebird.min.js"],"version":"3.4.3","mainfile":"bluebird.min.js"},{"files":["bluebird.core.js","bluebird.core.min.js","bluebird.js","bluebird.min.js"],"version":"3.4.2","mainfile":"bluebird.min.js"},{"files":["bluebird.core.js","bluebird.core.min.js","bluebird.js","bluebird.min.js"],"version":"3.4.1","mainfile":"bluebird.min.js"},{"files":["bluebird.core.js","bluebird.core.min.js","bluebird.js","bluebird.min.js"],"version":"3.4.0","mainfile":"bluebird.min.js"},{"files":["bluebird.core.js","bluebird.core.min.js","bluebird.js","bluebird.min.js"],"version":"3.3.5","mainfile":"bluebird.min.js"},{"files":["bluebird.core.js","bluebird.core.min.js","bluebird.js","bluebird.min.js"],"version":"3.3.4","mainfile":"bluebird.min.js"},{"files":["bluebird.core.js","bluebird.core.min.js","bluebird.js","bluebird.min.js"],"version":"3.3.3","mainfile":"bluebird.min.js"},{"files":["bluebird.core.js","bluebird.core.min.js","bluebird.js","bluebird.min.js"],"version":"3.3.2","mainfile":"bluebird.min.js"},{"files":["bluebird.core.js","bluebird.core.min.js","bluebird.js","bluebird.min.js"],"version":"3.3.1","mainfile":"bluebird.min.js"},{"files":["bluebird.core.js","bluebird.core.min.js","bluebird.js","bluebird.min.js"],"version":"3.3.0","mainfile":"bluebird.min.js"},{"files":["bluebird.core.js","bluebird.core.min.js","bluebird.js","bluebird.min.js"],"version":"3.2.2","mainfile":"bluebird.min.js"},{"files":["bluebird.core.js","bluebird.core.min.js","bluebird.js","bluebird.min.js"],"version":"3.2.1","mainfile":"bluebird.min.js"},{"files":["bluebird.core.js","bluebird.core.min.js","bluebird.js","bluebird.min.js"],"version":"3.2.0","mainfile":"bluebird.min.js"},{"files":["bluebird.core.js","bluebird.core.min.js","bluebird.js","bluebird.min.js"],"version":"3.1.5","mainfile":"bluebird.min.js"},{"files":["bluebird.core.js","bluebird.core.min.js","bluebird.js","bluebird.min.js"],"version":"3.1.4","mainfile":"bluebird.min.js"},{"files":["bluebird.js","bluebird.min.js"],"version":"3.1.3","mainfile":"bluebird.min.js"},{"files":["bluebird.js","bluebird.min.js"],"version":"3.1.2","mainfile":"bluebird.min.js"},{"files":["bluebird.js","bluebird.min.js"],"version":"3.1.1","mainfile":"bluebird.min.js"},{"files":["bluebird.js","bluebird.min.js"],"version":"3.1.0","mainfile":"bluebird.min.js"},{"files":["bluebird.js","bluebird.min.js"],"version":"3.0.6","mainfile":"bluebird.min.js"},{"files":["bluebird.js","bluebird.min.js"],"version":"3.0.5","mainfile":"bluebird.min.js"},{"files":["bluebird.js","bluebird.min.js"],"version":"3.0.4","mainfile":"bluebird.min.js"},{"files":["bluebird.js","bluebird.min.js"],"version":"3.0.3","mainfile":"bluebird.min.js"},{"files":["bluebird.js","bluebird.min.js"],"version":"3.0.2","mainfile":"bluebird.min.js"},{"files":["bluebird.js","bluebird.min.js"],"version":"3.0.1","mainfile":"bluebird.min.js"},{"files":["bluebird.js","bluebird.min.js"],"version":"3.0.0","mainfile":"bluebird.min.js"},{"files":["bluebird.js","bluebird.min.js"],"version":"2.9.9","mainfile":"bluebird.min.js"},{"files":["bluebird.js","bluebird.min.js"],"version":"2.9.8","mainfile":"bluebird.min.js"},{"files":["bluebird.js","bluebird.min.js"],"version":"2.9.7","mainfile":"bluebird.min.js"},{"files":["bluebird.js","bluebird.min.js"],"version":"2.9.6","mainfile":"bluebird.min.js"},{"files":["bluebird.js","bluebird.min.js"],"version":"2.9.5","mainfile":"bluebird.min.js"},{"files":["bluebird.js","bluebird.min.js"],"version":"2.9.4","mainfile":"bluebird.min.js"},{"files":["bluebird.js","bluebird.min.js"],"version":"2.9.34","mainfile":"bluebird.min.js"},{"files":["bluebird.js","bluebird.min.js"],"version":"2.9.33","mainfile":"bluebird.min.js"},{"files":["bluebird.js","bluebird.min.js"],"version":"2.9.32","mainfile":"bluebird.min.js"},{"files":["bluebird.js","bluebird.min.js"],"version":"2.9.31","mainfile":"bluebird.min.js"},{"files":["bluebird.js","bluebird.min.js"],"version":"2.9.30","mainfile":"bluebird.min.js"},{"files":["bluebird.js","bluebird.min.js"],"version":"2.9.3","mainfile":"bluebird.min.js"},{"files":["bluebird.js","bluebird.min.js"],"version":"2.9.29","mainfile":"bluebird.min.js"},{"files":["bluebird.js","bluebird.min.js"],"version":"2.9.28","mainfile":"bluebird.min.js"},{"files":["bluebird.js","bluebird.min.js"],"version":"2.9.27","mainfile":"bluebird.min.js"},{"files":["bluebird.js","bluebird.min.js"],"version":"2.9.26","mainfile":"bluebird.min.js"},{"files":["bluebird.js","bluebird.min.js"],"version":"2.9.25","mainfile":"bluebird.min.js"},{"files":["bluebird.js","bluebird.min.js"],"version":"2.9.24","mainfile":"bluebird.min.js"},{"files":["bluebird.js","bluebird.min.js"],"version":"2.9.23","mainfile":"bluebird.min.js"},{"files":["bluebird.js","bluebird.min.js"],"version":"2.9.22","mainfile":"bluebird.min.js"},{"files":["bluebird.js","bluebird.min.js"],"version":"2.9.21","mainfile":"bluebird.min.js"},{"files":["bluebird.js","bluebird.min.js"],"version":"2.9.20","mainfile":"bluebird.min.js"},{"files":["bluebird.js","bluebird.min.js"],"version":"2.9.2","mainfile":"bluebird.min.js"},{"files":["bluebird.js","bluebird.min.js"],"version":"2.9.19","mainfile":"bluebird.min.js"},{"files":["bluebird.js","bluebird.min.js"],"version":"2.9.18","mainfile":"bluebird.min.js"},{"files":["bluebird.js","bluebird.min.js"],"version":"2.9.17","mainfile":"bluebird.min.js"}],"versions":["3.4.7","3.4.6","3.4.5","3.4.4","3.4.3","3.4.2","3.4.1","3.4.0","3.3.5","3.3.4","3.3.3","3.3.2","3.3.1","3.3.0","3.2.2","3.2.1","3.2.0","3.1.5","3.1.4","3.1.3","3.1.2","3.1.1","3.1.0","3.0.6","3.0.5","3.0.4","3.0.3","3.0.2","3.0.1","3.0.0","2.11.0","2.10.2","2.10.1","2.10.0","2.9.34","2.9.33","2.9.32","2.9.31","2.9.30","2.9.29","2.9.28","2.9.27","2.9.26","2.9.25","2.9.24","2.9.23","2.9.22","2.9.21","2.9.20","2.9.19","2.9.18","2.9.17","2.9.16","2.9.15","2.9.14","2.9.13","2.9.12","2.9.11","2.9.10","2.9.9","2.9.8","2.9.7","2.9.6","2.9.5","2.9.4","2.9.3","2.9.2","2.9.1","2.9.0","2.8.2","2.8.1","2.8.0","2.7.1","2.7.0","2.6.4","2.6.3","2.6.2","2.6.1","2.6.0","2.5.3","2.5.2","2.5.1","2.5.0","2.4.3","2.4.2","2.4.1","2.4.0","2.3.11","2.3.10","2.3.9","2.3.6","1.2.2","1.2.1","1.0.0","0.7.10-1"],"zip":"bluebird.zip","mainfile":"bluebird.min.js","author":{"name":"Petka Antonov","email":"petka_antonov@hotmail.com","url":"https://github.com/petkaantonov/"},"lastversion":"3.4.7","homepage":null,"description":"Full featured Promises/A+ implementation with exceptionally good performance","github":"git://github.com/petkaantonov/bluebird.git"}