{"name":"bigscreen","assets":[{"files":["bigscreen.min.js"],"version":"1.0.2","mainfile":"bigscreen.min.js"},{"files":["bigscreen.js","bigscreen.min.js"],"version":"2.0.0","mainfile":"bigscreen.min.js"},{"files":["bigscreen.js","bigscreen.min.js"],"version":"2.0.2","mainfile":"bigscreen.min.js"},{"files":["bigscreen.js","bigscreen.min.js"],"version":"2.0.4","mainfile":"bigscreen.min.js"},{"files":["bigscreen.min.js","bigscreen.min.js.map"],"version":"2.0.5","mainfile":"bigscreen.min.js"}],"versions":["2.0.5","2.0.4","2.0.2","2.0.0","1.0.2"],"zip":"bigscreen.zip","author":"Brad Dougherty","github":"https://github.com/bdougherty/BigScreen","homepage":"http://brad.is/coding/BigScreen/","description":"A simple library for using the JavaScript Fullscreen API.","mainfile":"bigscreen.min.js","lastversion":"2.0.5"}