{"name":"grd","assets":[{"files":["grd.css"],"version":"1.0.1","mainfile":"grd.css"},{"files":["grd.css"],"version":"1.0.2","mainfile":"grd.css"},{"files":["grd.css"],"version":"1.1.0","mainfile":"grd.css"},{"files":["grd.css"],"version":"1.1.1","mainfile":"grd.css"},{"files":["grd.css"],"version":"1.2.0","mainfile":"grd.css"},{"files":["grd.css"],"version":"1.2.1","mainfile":"grd.css"},{"files":["grd.css"],"version":"1.2.2","mainfile":"grd.css"},{"files":["grd.css"],"version":"1.2.3","mainfile":"grd.css"}],"versions":["1.2.3","1.2.2","1.2.1","1.2.0","1.1.1","1.1.0","1.0.2","1.0.1"],"zip":"grd.zip","mainfile":"grd.css","author":{"name":"Shogo Sensui","email":"shogo.sensui@gmail.com","url":"https://github.com/1000ch"},"lastversion":"1.2.3","homepage":"https://1000ch.github.io/grd","description":"A CSS grid framework using Flexbox.","github":"https://github.com/1000ch/grd"}